<lote><sms><seunum>3291791</seunum><celular>11973457386</celular><mensagem>Mensagem da campanha url-m.com/m/cPVpC</mensagem><agendamento>2017-09-15 16:16</agendamento></sms><sms><seunum>3291792</seunum><celular>11973458007</celular><mensagem>Mensagem da campanha url-m.com/m/cPVpD</mensagem><agendamento>2017-09-15 16:16</agendamento></sms><sms><seunum>3291793</seunum><celular>11973458964</celular><mensagem>Mensagem da campanha url-m.com/m/cPVpE</mensagem><agendamento>2017-09-15 16:16</agendamento></sms><sms><seunum>3291794</seunum><celular>11973464007</celular><mensagem>Mensagem da campanha url-m.com/m/cPVpF</mensagem><agendamento>2017-09-15 16:16</agendamento></sms><sms><seunum>3291795</seunum><celular>11973466412</celular><mensagem>Mensagem da campanha url-m.com/m/cPVpG</mensagem><agendamento>2017-09-15 16:16</agendamento></sms><sms><seunum>3291796</seunum><celular>11973467335</celular><mensagem>Mensagem da campanha url-m.com/m/cPVpH</mensagem><agendamento>2017-09-15 16:16</agendamento></sms><sms><seunum>3291797</seunum><celular>11973468190</celular><mensagem>Mensagem da campanha url-m.com/m/cPVpI</mensagem><agendamento>2017-09-15 16:16</agendamento></sms><sms><seunum>3291798</seunum><celular>11973468750</celular><mensagem>Mensagem da campanha url-m.com/m/cPVpJ</mensagem><agendamento>2017-09-15 16:16</agendamento></sms><sms><seunum>3291799</seunum><celular>11973468935</celular><mensagem>Mensagem da campanha url-m.com/m/cPVpK</mensagem><agendamento>2017-09-15 16:16</agendamento></sms><sms><seunum>3291800</seunum><celular>11973468948</celular><mensagem>Mensagem da campanha url-m.com/m/cPVpL</mensagem><agendamento>2017-09-15 16:16</agendamento></sms><sms><seunum>3291801</seunum><celular>11973470661</celular><mensagem>Mensagem da campanha url-m.com/m/cPVpM</mensagem><agendamento>2017-09-15 16:16</agendamento></sms><sms><seunum>3291802</seunum><celular>11973471672</celular><mensagem>Mensagem da campanha url-m.com/m/cPVpN</mensagem><agendamento>2017-09-15 16:16</agendamento></sms><sms><seunum>3291803</seunum><celular>11973472230</celular><mensagem>Mensagem da campanha url-m.com/m/cPVpO</mensagem><agendamento>2017-09-15 16:16</agendamento></sms><sms><seunum>3291804</seunum><celular>11973472272</celular><mensagem>Mensagem da campanha url-m.com/m/cPVpP</mensagem><agendamento>2017-09-15 16:16</agendamento></sms><sms><seunum>3291805</seunum><celular>11973472853</celular><mensagem>Mensagem da campanha url-m.com/m/cPVpQ</mensagem><agendamento>2017-09-15 16:16</agendamento></sms><sms><seunum>3291806</seunum><celular>11973472961</celular><mensagem>Mensagem da campanha url-m.com/m/cPVpR</mensagem><agendamento>2017-09-15 16:16</agendamento></sms><sms><seunum>3291807</seunum><celular>11973475139</celular><mensagem>Mensagem da campanha url-m.com/m/cPVpS</mensagem><agendamento>2017-09-15 16:16</agendamento></sms><sms><seunum>3291808</seunum><celular>11973475534</celular><mensagem>Mensagem da campanha url-m.com/m/cPVpT</mensagem><agendamento>2017-09-15 16:16</agendamento></sms><sms><seunum>3291809</seunum><celular>11973477588</celular><mensagem>Mensagem da campanha url-m.com/m/cPVpU</mensagem><agendamento>2017-09-15 16:16</agendamento></sms><sms><seunum>3291810</seunum><celular>11973477673</celular><mensagem>Mensagem da campanha url-m.com/m/cPVpV</mensagem><agendamento>2017-09-15 16:16</agendamento></sms><sms><seunum>3291811</seunum><celular>11973478091</celular><mensagem>Mensagem da campanha url-m.com/m/cPVpW</mensagem><agendamento>2017-09-15 16:16</agendamento></sms><sms><seunum>3291812</seunum><celular>11973478515</celular><mensagem>Mensagem da campanha url-m.com/m/cPVpX</mensagem><agendamento>2017-09-15 16:16</agendamento></sms><sms><seunum>3291813</seunum><celular>11973478741</celular><mensagem>Mensagem da campanha url-m.com/m/cPVpY</mensagem><agendamento>2017-09-15 16:16</agendamento></sms><sms><seunum>3291814</seunum><celular>11973479254</celular><mensagem>Mensagem da campanha url-m.com/m/cPVpZ</mensagem><agendamento>2017-09-15 16:16</agendamento></sms><sms><seunum>3291815</seunum><celular>11973481293</celular><mensagem>Mensagem da campanha url-m.com/m/cPVqa</mensagem><agendamento>2017-09-15 16:16</agendamento></sms><sms><seunum>3291816</seunum><celular>11973481510</celular><mensagem>Mensagem da campanha url-m.com/m/cPVqb</mensagem><agendamento>2017-09-15 16:16</agendamento></sms><sms><seunum>3291817</seunum><celular>11973481705</celular><mensagem>Mensagem da campanha url-m.com/m/cPVqc</mensagem><agendamento>2017-09-15 16:16</agendamento></sms><sms><seunum>3291818</seunum><celular>11973482031</celular><mensagem>Mensagem da campanha url-m.com/m/cPVqd</mensagem><agendamento>2017-09-15 16:16</agendamento></sms><sms><seunum>3291819</seunum><celular>11973482901</celular><mensagem>Mensagem da campanha url-m.com/m/cPVqe</mensagem><agendamento>2017-09-15 16:16</agendamento></sms><sms><seunum>3291820</seunum><celular>11973484892</celular><mensagem>Mensagem da campanha url-m.com/m/cPVqf</mensagem><agendamento>2017-09-15 16:16</agendamento></sms><sms><seunum>3291821</seunum><celular>11973486469</celular><mensagem>Mensagem da campanha url-m.com/m/cPVqg</mensagem><agendamento>2017-09-15 16:16</agendamento></sms><sms><seunum>3291822</seunum><celular>11973487129</celular><mensagem>Mensagem da campanha url-m.com/m/cPVqh</mensagem><agendamento>2017-09-15 16:16</agendamento></sms><sms><seunum>3291823</seunum><celular>11973487604</celular><mensagem>Mensagem da campanha url-m.com/m/cPVqi</mensagem><agendamento>2017-09-15 16:16</agendamento></sms><sms><seunum>3291824</seunum><celular>11973489061</celular><mensagem>Mensagem da campanha url-m.com/m/cPVqj</mensagem><agendamento>2017-09-15 16:16</agendamento></sms><sms><seunum>3291825</seunum><celular>11973490378</celular><mensagem>Mensagem da campanha url-m.com/m/cPVqk</mensagem><agendamento>2017-09-15 16:16</agendamento></sms><sms><seunum>3291826</seunum><celular>11973492838</celular><mensagem>Mensagem da campanha url-m.com/m/cPVql</mensagem><agendamento>2017-09-15 16:16</agendamento></sms><sms><seunum>3291827</seunum><celular>11973493995</celular><mensagem>Mensagem da campanha url-m.com/m/cPVqm</mensagem><agendamento>2017-09-15 16:16</agendamento></sms><sms><seunum>3291828</seunum><celular>11973494943</celular><mensagem>Mensagem da campanha url-m.com/m/cPVqn</mensagem><agendamento>2017-09-15 16:16</agendamento></sms><sms><seunum>3291829</seunum><celular>11973496781</celular><mensagem>Mensagem da campanha url-m.com/m/cPVqo</mensagem><agendamento>2017-09-15 16:16</agendamento></sms><sms><seunum>3291830</seunum><celular>11973497330</celular><mensagem>Mensagem da campanha url-m.com/m/cPVqp</mensagem><agendamento>2017-09-15 16:16</agendamento></sms><sms><seunum>3291831</seunum><celular>11973499499</celular><mensagem>Mensagem da campanha url-m.com/m/cPVqq</mensagem><agendamento>2017-09-15 16:16</agendamento></sms><sms><seunum>3291832</seunum><celular>11973500025</celular><mensagem>Mensagem da campanha url-m.com/m/cPVqr</mensagem><agendamento>2017-09-15 16:16</agendamento></sms><sms><seunum>3291833</seunum><celular>11973501388</celular><mensagem>Mensagem da campanha url-m.com/m/cPVqs</mensagem><agendamento>2017-09-15 16:16</agendamento></sms><sms><seunum>3291834</seunum><celular>11973501522</celular><mensagem>Mensagem da campanha url-m.com/m/cPVqt</mensagem><agendamento>2017-09-15 16:16</agendamento></sms><sms><seunum>3291835</seunum><celular>11973501796</celular><mensagem>Mensagem da campanha url-m.com/m/cPVqu</mensagem><agendamento>2017-09-15 16:16</agendamento></sms><sms><seunum>3291836</seunum><celular>11973503335</celular><mensagem>Mensagem da campanha url-m.com/m/cPVqv</mensagem><agendamento>2017-09-15 16:16</agendamento></sms><sms><seunum>3291837</seunum><celular>11973503530</celular><mensagem>Mensagem da campanha url-m.com/m/cPVqw</mensagem><agendamento>2017-09-15 16:16</agendamento></sms><sms><seunum>3291838</seunum><celular>11973507291</celular><mensagem>Mensagem da campanha url-m.com/m/cPVqx</mensagem><agendamento>2017-09-15 16:16</agendamento></sms><sms><seunum>3291839</seunum><celular>11973507484</celular><mensagem>Mensagem da campanha url-m.com/m/cPVqy</mensagem><agendamento>2017-09-15 16:16</agendamento></sms><sms><seunum>3291840</seunum><celular>11973507962</celular><mensagem>Mensagem da campanha url-m.com/m/cPVqz</mensagem><agendamento>2017-09-15 16:16</agendamento></sms><sms><seunum>3291841</seunum><celular>11973508186</celular><mensagem>Mensagem da campanha url-m.com/m/cPVq0</mensagem><agendamento>2017-09-15 16:16</agendamento></sms><sms><seunum>3291842</seunum><celular>11973508225</celular><mensagem>Mensagem da campanha url-m.com/m/cPVq1</mensagem><agendamento>2017-09-15 16:16</agendamento></sms><sms><seunum>3291843</seunum><celular>11973510737</celular><mensagem>Mensagem da campanha url-m.com/m/cPVq2</mensagem><agendamento>2017-09-15 16:16</agendamento></sms><sms><seunum>3291844</seunum><celular>11973511047</celular><mensagem>Mensagem da campanha url-m.com/m/cPVq3</mensagem><agendamento>2017-09-15 16:16</agendamento></sms><sms><seunum>3291845</seunum><celular>11973511911</celular><mensagem>Mensagem da campanha url-m.com/m/cPVq4</mensagem><agendamento>2017-09-15 16:16</agendamento></sms><sms><seunum>3291846</seunum><celular>11973512526</celular><mensagem>Mensagem da campanha url-m.com/m/cPVq5</mensagem><agendamento>2017-09-15 16:16</agendamento></sms><sms><seunum>3291847</seunum><celular>11973515971</celular><mensagem>Mensagem da campanha url-m.com/m/cPVq6</mensagem><agendamento>2017-09-15 16:16</agendamento></sms><sms><seunum>3291848</seunum><celular>11973516908</celular><mensagem>Mensagem da campanha url-m.com/m/cPVq7</mensagem><agendamento>2017-09-15 16:16</agendamento></sms><sms><seunum>3291849</seunum><celular>11973517300</celular><mensagem>Mensagem da campanha url-m.com/m/cPVq8</mensagem><agendamento>2017-09-15 16:16</agendamento></sms><sms><seunum>3291850</seunum><celular>11973517568</celular><mensagem>Mensagem da campanha url-m.com/m/cPVq9</mensagem><agendamento>2017-09-15 16:16</agendamento></sms><sms><seunum>3291851</seunum><celular>11973518838</celular><mensagem>Mensagem da campanha url-m.com/m/cPVqA</mensagem><agendamento>2017-09-15 16:16</agendamento></sms><sms><seunum>3291852</seunum><celular>11973519044</celular><mensagem>Mensagem da campanha url-m.com/m/cPVqB</mensagem><agendamento>2017-09-15 16:16</agendamento></sms><sms><seunum>3291853</seunum><celular>11973519204</celular><mensagem>Mensagem da campanha url-m.com/m/cPVqC</mensagem><agendamento>2017-09-15 16:16</agendamento></sms><sms><seunum>3291854</seunum><celular>11973520038</celular><mensagem>Mensagem da campanha url-m.com/m/cPVqD</mensagem><agendamento>2017-09-15 16:16</agendamento></sms><sms><seunum>3291855</seunum><celular>11973522928</celular><mensagem>Mensagem da campanha url-m.com/m/cPVqE</mensagem><agendamento>2017-09-15 16:16</agendamento></sms><sms><seunum>3291856</seunum><celular>11973525109</celular><mensagem>Mensagem da campanha url-m.com/m/cPVqF</mensagem><agendamento>2017-09-15 16:16</agendamento></sms><sms><seunum>3291857</seunum><celular>11973525681</celular><mensagem>Mensagem da campanha url-m.com/m/cPVqG</mensagem><agendamento>2017-09-15 16:16</agendamento></sms><sms><seunum>3291858</seunum><celular>11973526315</celular><mensagem>Mensagem da campanha url-m.com/m/cPVqH</mensagem><agendamento>2017-09-15 16:16</agendamento></sms><sms><seunum>3291859</seunum><celular>11973526334</celular><mensagem>Mensagem da campanha url-m.com/m/cPVqI</mensagem><agendamento>2017-09-15 16:16</agendamento></sms><sms><seunum>3291860</seunum><celular>11973528115</celular><mensagem>Mensagem da campanha url-m.com/m/cPVqJ</mensagem><agendamento>2017-09-15 16:16</agendamento></sms><sms><seunum>3291861</seunum><celular>11973529728</celular><mensagem>Mensagem da campanha url-m.com/m/cPVqK</mensagem><agendamento>2017-09-15 16:16</agendamento></sms><sms><seunum>3291862</seunum><celular>11973529966</celular><mensagem>Mensagem da campanha url-m.com/m/cPVqL</mensagem><agendamento>2017-09-15 16:16</agendamento></sms><sms><seunum>3291863</seunum><celular>11973530200</celular><mensagem>Mensagem da campanha url-m.com/m/cPVqM</mensagem><agendamento>2017-09-15 16:16</agendamento></sms><sms><seunum>3291864</seunum><celular>11973532175</celular><mensagem>Mensagem da campanha url-m.com/m/cPVqN</mensagem><agendamento>2017-09-15 16:16</agendamento></sms><sms><seunum>3291865</seunum><celular>11973532234</celular><mensagem>Mensagem da campanha url-m.com/m/cPVqO</mensagem><agendamento>2017-09-15 16:16</agendamento></sms><sms><seunum>3291866</seunum><celular>11973532894</celular><mensagem>Mensagem da campanha url-m.com/m/cPVqP</mensagem><agendamento>2017-09-15 16:16</agendamento></sms><sms><seunum>3291867</seunum><celular>11973533535</celular><mensagem>Mensagem da campanha url-m.com/m/cPVqQ</mensagem><agendamento>2017-09-15 16:16</agendamento></sms><sms><seunum>3291868</seunum><celular>11973533636</celular><mensagem>Mensagem da campanha url-m.com/m/cPVqR</mensagem><agendamento>2017-09-15 16:16</agendamento></sms><sms><seunum>3291869</seunum><celular>11973533919</celular><mensagem>Mensagem da campanha url-m.com/m/cPVqS</mensagem><agendamento>2017-09-15 16:16</agendamento></sms><sms><seunum>3291870</seunum><celular>11973534224</celular><mensagem>Mensagem da campanha url-m.com/m/cPVqT</mensagem><agendamento>2017-09-15 16:16</agendamento></sms><sms><seunum>3291871</seunum><celular>11973534673</celular><mensagem>Mensagem da campanha url-m.com/m/cPVqU</mensagem><agendamento>2017-09-15 16:16</agendamento></sms><sms><seunum>3291872</seunum><celular>11973534838</celular><mensagem>Mensagem da campanha url-m.com/m/cPVqV</mensagem><agendamento>2017-09-15 16:16</agendamento></sms><sms><seunum>3291873</seunum><celular>11973535163</celular><mensagem>Mensagem da campanha url-m.com/m/cPVqW</mensagem><agendamento>2017-09-15 16:16</agendamento></sms><sms><seunum>3291874</seunum><celular>11973535346</celular><mensagem>Mensagem da campanha url-m.com/m/cPVqX</mensagem><agendamento>2017-09-15 16:16</agendamento></sms><sms><seunum>3291875</seunum><celular>11973536089</celular><mensagem>Mensagem da campanha url-m.com/m/cPVqY</mensagem><agendamento>2017-09-15 16:16</agendamento></sms><sms><seunum>3291876</seunum><celular>11973538457</celular><mensagem>Mensagem da campanha url-m.com/m/cPVqZ</mensagem><agendamento>2017-09-15 16:16</agendamento></sms><sms><seunum>3291877</seunum><celular>11973538555</celular><mensagem>Mensagem da campanha url-m.com/m/cPVra</mensagem><agendamento>2017-09-15 16:16</agendamento></sms><sms><seunum>3291878</seunum><celular>11973538688</celular><mensagem>Mensagem da campanha url-m.com/m/cPVrb</mensagem><agendamento>2017-09-15 16:16</agendamento></sms><sms><seunum>3291879</seunum><celular>11973540146</celular><mensagem>Mensagem da campanha url-m.com/m/cPVrc</mensagem><agendamento>2017-09-15 16:16</agendamento></sms><sms><seunum>3291880</seunum><celular>11973542323</celular><mensagem>Mensagem da campanha url-m.com/m/cPVrd</mensagem><agendamento>2017-09-15 16:16</agendamento></sms><sms><seunum>3291881</seunum><celular>11973542325</celular><mensagem>Mensagem da campanha url-m.com/m/cPVre</mensagem><agendamento>2017-09-15 16:16</agendamento></sms><sms><seunum>3291882</seunum><celular>11973544878</celular><mensagem>Mensagem da campanha url-m.com/m/cPVrf</mensagem><agendamento>2017-09-15 16:16</agendamento></sms><sms><seunum>3291883</seunum><celular>11973548158</celular><mensagem>Mensagem da campanha url-m.com/m/cPVrg</mensagem><agendamento>2017-09-15 16:16</agendamento></sms><sms><seunum>3291884</seunum><celular>11973548637</celular><mensagem>Mensagem da campanha url-m.com/m/cPVrh</mensagem><agendamento>2017-09-15 16:16</agendamento></sms><sms><seunum>3291885</seunum><celular>11973549709</celular><mensagem>Mensagem da campanha url-m.com/m/cPVri</mensagem><agendamento>2017-09-15 16:16</agendamento></sms><sms><seunum>3291886</seunum><celular>11973549835</celular><mensagem>Mensagem da campanha url-m.com/m/cPVrj</mensagem><agendamento>2017-09-15 16:16</agendamento></sms><sms><seunum>3291887</seunum><celular>11973549894</celular><mensagem>Mensagem da campanha url-m.com/m/cPVrk</mensagem><agendamento>2017-09-15 16:16</agendamento></sms><sms><seunum>3291888</seunum><celular>11973549936</celular><mensagem>Mensagem da campanha url-m.com/m/cPVrl</mensagem><agendamento>2017-09-15 16:16</agendamento></sms><sms><seunum>3291889</seunum><celular>11973551275</celular><mensagem>Mensagem da campanha url-m.com/m/cPVrm</mensagem><agendamento>2017-09-15 16:16</agendamento></sms><sms><seunum>3291890</seunum><celular>11973553658</celular><mensagem>Mensagem da campanha url-m.com/m/cPVrn</mensagem><agendamento>2017-09-15 16:16</agendamento></sms></lote>